neural_mmo/__init__.py
neural_mmo/_version.py
neural_mmo/forge/__init__.py
neural_mmo/forge/blade/__init__.py
neural_mmo/forge/blade/core/__init__.py
neural_mmo/forge/blade/core/config.py
neural_mmo/forge/blade/core/map.py
neural_mmo/forge/blade/core/realm.py
neural_mmo/forge/blade/core/terrain.py
neural_mmo/forge/blade/core/tile.py
neural_mmo/forge/blade/core/market/__init__.py
neural_mmo/forge/blade/core/market/config.py
neural_mmo/forge/blade/core/market/new_visualizer.py
neural_mmo/forge/blade/core/market/visualizer.py
neural_mmo/forge/blade/entity/__init__.py
neural_mmo/forge/blade/entity/entity.py
neural_mmo/forge/blade/entity/npc.py
neural_mmo/forge/blade/entity/player.py
neural_mmo/forge/blade/hook/__init__.py
neural_mmo/forge/blade/hook/item.py
neural_mmo/forge/blade/hook/modules.py
neural_mmo/forge/blade/io/__init__.py
neural_mmo/forge/blade/io/comparable.py
neural_mmo/forge/blade/io/node.py
neural_mmo/forge/blade/io/utils.py
neural_mmo/forge/blade/io/action/__init__.py
neural_mmo/forge/blade/io/action/node.py
neural_mmo/forge/blade/io/action/static.py
neural_mmo/forge/blade/io/stimulus/__init__.py
neural_mmo/forge/blade/io/stimulus/dynamic.py
neural_mmo/forge/blade/io/stimulus/hook.py
neural_mmo/forge/blade/io/stimulus/node.py
neural_mmo/forge/blade/io/stimulus/static.py
neural_mmo/forge/blade/lib/__init__.py
neural_mmo/forge/blade/lib/comms.py
neural_mmo/forge/blade/lib/enums.py
neural_mmo/forge/blade/lib/log.py
neural_mmo/forge/blade/lib/material.py
neural_mmo/forge/blade/lib/multiset.py
neural_mmo/forge/blade/lib/overlay.py
neural_mmo/forge/blade/lib/priorityqueue.py
neural_mmo/forge/blade/lib/ray.py
neural_mmo/forge/blade/lib/stattrak.py
neural_mmo/forge/blade/lib/utils.py
neural_mmo/forge/blade/systems/__init__.py
neural_mmo/forge/blade/systems/achievement.py
neural_mmo/forge/blade/systems/combat.py
neural_mmo/forge/blade/systems/droptable.py
neural_mmo/forge/blade/systems/equipment.py
neural_mmo/forge/blade/systems/exchange.py
neural_mmo-1.5.2.2.dist-info/LICENSE
neural_mmo-1.5.2.2.dist-info/METADATA
neural_mmo-1.5.2.2.dist-info/WHEEL
neural_mmo-1.5.2.2.dist-info/entry_points.txt
neural_mmo-1.5.2.2.dist-info/top_level.txt
neural_mmo-1.5.2.2.dist-info/RECORD
