Metadata-Version: 2.1
Name: neural-mmo
Version: 1.5.2.2
Summary: Neural MMO is a massively multiagent environment for artificial intelligence research inspired by Massively Multiplayer Online (MMO) role-playing games
Home-page: https://github.com/jsuarez5341/neural-mmo
Author: Joseph Suarez
Author-email: sealsuarez@gmail.com
License: MIT
Keywords: Neural MMO,MMO
Platform: UNKNOWN
Classifier: Development Status :: 3 - Alpha
Classifier: Intended Audience :: Developers
Classifier: Environment :: Console
Classifier: License :: OSI Approved :: MIT License
Classifier: Programming Language :: Python :: 3.6
Classifier: Programming Language :: Python :: 3.7
Classifier: Programming Language :: Python :: 3.8
Classifier: Programming Language :: Python :: 3.9
Requires-Python: >=3.6
Requires-Dist: fire (==0.4.0)
Requires-Dist: setproctitle (==1.1.10)
Requires-Dist: autobahn (==19.3.3)
Requires-Dist: Twisted (==19.2.0)
Requires-Dist: gym (==0.17.2)
Requires-Dist: vec-noise (==1.1.4)
Requires-Dist: bokeh (==2.2.3)
Requires-Dist: imageio (==2.8.0)
Requires-Dist: sphinx-rtd-theme (==0.5.1)
Requires-Dist: tqdm (==4.61.1)
Requires-Dist: matplotlib (==3.1.3)
Provides-Extra: rllib
Requires-Dist: ray[rllib] (==1.4.0) ; extra == 'rllib'
Requires-Dist: tensorflow (==2.4.1) ; extra == 'rllib'
Requires-Dist: dm-tree (==0.1.5) ; extra == 'rllib'
Requires-Dist: setproctitle (==1.1.10) ; extra == 'rllib'
Requires-Dist: torch ; extra == 'rllib'
